README.rst
setup.py
redis_pubsub_helper.egg-info/PKG-INFO
redis_pubsub_helper.egg-info/SOURCES.txt
redis_pubsub_helper.egg-info/dependency_links.txt
redis_pubsub_helper.egg-info/requires.txt
redis_pubsub_helper.egg-info/top_level.txt
redispubsub/__init__.py
redispubsub/core.py
redispubsub/version.txt