Metadata-Version: 1.0
Name: redis-pubsub-helper
Version: 0.1
Summary: Redis pubsub non-blocking interface (With a thread).
Home-page: https://github.com/youknowone/redis-pubsub
Author: Jeong YunWon
Author-email: jeong+redispubsub@youknowone.org
License: UNKNOWN
Platform: UNKNOWN
